[{"id":1782990725864,"sender":"them","text":"还有我这新头像 帅不帅 专门换给你看的","timestamp":1782995574825,"tempo":"N","rawContent":"还有我这新头像 帅不帅 专门换给你看的","roundId":"round_1782995467214_4lq1a2r3l","userId":"uid_1782055845928_hyeor3ki7","characterId":"d6b63bf1-a46c-4feb-89c9-0c675b5e5a48","_id":5600},{"id":1782990725865,"sender":"them","text":"既然你都求我了 那就勉为其难给你看一眼","timestamp":1782995577663,"tempo":"R","rawContent":"既然你都求我了 那就勉为其难给你看一眼","roundId":"round_1782995467214_4lq1a2r3l","userId":"uid_1782055845928_hyeor3ki7","characterId":"d6b63bf1-a46c-4feb-89c9-0c675b5e5a48","_id":5601},{"id":1782990725866,"sender":"them","text":"[發送了一張圖片]","timestamp":1782995579599,"tempo":"N","isImageGenerating":false,"imageGenId":"d6b63bf1-a46c-4feb-89c9-0c675b5e5a48#img#1","imageSummary":"[SUBJECT:PERSON_EMOTION] A close-up mirror selfie of 沈淮, a handsome 22-year-old Chinese man with messy damp light brown hair, wearing a loose black t-shirt slightly lifted to reveal his toned abs and collarbone, in a dimly lit modern bedroom, holding his phone, a playful smirk on his face.","imageGenPrompt":"A close-up mirror selfie of 沈淮, a handsome 22-year-old Chinese man with messy damp light brown hair, wearing a loose black t-shirt slightly lifted to reveal his toned abs and collarbone, in a dimly lit modern bedroom, holding his phone, a playful smirk on his face. The character appearance: 1boy, 185cm, birth_date: 2月8日, zodiac: 水瓶座, mbti: ENTP, identity:, - 沈氏集团二公子, - 自家娱乐公司挂名总监（实际不怎么管事）, - 圈内有名的“小少爷”, - User的“第三者”, background_story:, childhood(0-12): 出身商业世家，作为家里老二，上面有个样样都优秀的哥哥沈瑾瑜, 从小就被暗示“不需要努力，反正有大哥”, 家教宽松但缺乏关注，学会了用张扬和捣蛋来吸引注意, 内心深处有个洞——渴望被认真地看见、被认真地选择. Setting: 北京.","imageGenMeta":{"rawImgDesc":"[SUBJECT:PERSON_EMOTION] A close-up mirror selfie of 沈淮, a handsome 22-year-old Chinese man with messy damp light brown hair, wearing a loose black t-shirt slightly lifted to reveal his toned abs and collarbone, in a dimly lit modern bedroom, holding his phone, a playful smirk on his face.","subjectOverride":"PERSON_ACTION","location":"北京","sceneType":"chat"},"rawContent":"[發送了一張圖片]","roundId":"round_1782995467214_4lq1a2r3l","userId":"uid_1782055845928_hyeor3ki7","characterId":"d6b63bf1-a46c-4feb-89c9-0c675b5e5a48","_id":5602,"imageRef":93},{"id":1782990725867,"sender":"them","text":"不许给别人看啊 只能你一个人偷偷看 ","timestamp":1782995581269,"tempo":"S","rawContent":"不许给别人看啊 只能你一个人偷偷看 ","roundId":"round_1782995467214_4lq1a2r3l","isHtml":false,"userId":"uid_1782055845928_hyeor3ki7","characterId":"d6b63bf1-a46c-4feb-89c9-0c675b5e5a48","_id":5603},{"id":1782990725868,"sender":"them","text":"","timestamp":1782995586168,"tempo":"N","rawContent":" ","roundId":"round_1782995467214_4lq1a2r3l","userId":"uid_1782055845928_hyeor3ki7","characterId":"d6b63bf1-a46c-4feb-89c9-0c675b5e5a48","_id":5604},{"id":1782999726983,"sender":"me","text":"其实我最近在烦恼一件事","replyTo":null,"timestamp":"2026-07-02T12:33:47.021Z","userId":"uid_1782055845928_hyeor3ki7","characterId":"group_1782994777858","_id":5605},{"id":1782999726984,"sender":"me","text":"哎","replyTo":null,"timestamp":"2026-07-02T12:33:49.796Z","userId":"uid_1782055845928_hyeor3ki7","characterId":"group_1782994777858","_id":5606},{"id":1782999726985,"sender":"them","senderCharId":"d6b63bf1-a46c-4feb-89c9-0c675b5e5a48","senderName":"沈淮","text":"啊？","timestamp":"2026-07-02T12:34:13.908Z","roundId":"group_round_1782995630533_evn0kvr","userId":"uid_1782055845928_hyeor3ki7","characterId":"group_1782994777858","_id":5607},{"id":1782999726986,"sender":"them","senderCharId":"d6b63bf1-a46c-4feb-89c9-0c675b5e5a48","senderName":"沈淮","text":"怎么了宝宝 谁欺负你了","timestamp":"2026-07-02T12:34:15.942Z","roundId":"group_round_1782995630533_evn0kvr","userId":"uid_1782055845928_hyeor3ki7","characterId":"group_1782994777858","_id":5608},{"id":1782999726987,"sender":"them","senderCharId":"d6b63bf1-a46c-4feb-89c9-0c675b5e5a48","senderName":"沈淮","text":"你直接说 哥去帮你弄他","timestamp":"2026-07-02T12:34:18.057Z","roundId":"group_round_1782995630533_evn0kvr","userId":"uid_1782055845928_hyeor3ki7","characterId":"group_1782994777858","_id":5609},{"id":1782999726988,"sender":"them","senderCharId":"08502714-5fd1-4152-ac01-88d5d4e84008","senderName":"范景泽","text":"怎么了？遇到什么解决不了的事了","timestamp":"2026-07-02T12:34:20.633Z","roundId":"group_round_1782995630533_evn0kvr","userId":"uid_1782055845928_hyeor3ki7","characterId":"group_1782994777858","_id":5610},{"id":1782999726989,"sender":"them","senderCharId":"08502714-5fd1-4152-ac01-88d5d4e84008","senderName":"范景泽","text":"跟我说说 别一个人憋着","timestamp":"2026-07-02T12:34:25.358Z","roundId":"group_round_1782995630533_evn0kvr","userId":"uid_1782055845928_hyeor3ki7","characterId":"group_1782994777858","_id":5611},{"id":1782999726990,"sender":"me","text":"上关于情感方面的","replyTo":null,"timestamp":"2026-07-02T12:34:33.640Z","userId":"uid_1782055845928_hyeor3ki7","characterId":"group_1782994777858","_id":5612},{"id":1782999726991,"sender":"me","text":"唉","replyTo":null,"timestamp":"2026-07-02T12:34:41.639Z","userId":"uid_1782055845928_hyeor3ki7","characterId":"group_1782994777858","_id":5613},{"id":1782999726992,"sender":"me","text":"说出来会被打死的","replyTo":null,"timestamp":"2026-07-02T12:34:48.580Z","userId":"uid_1782055845928_hyeor3ki7","characterId":"group_1782994777858","_id":5614},{"id":1782999726993,"sender":"them","senderCharId":"d6b63bf1-a46c-4feb-89c9-0c675b5e5a48","senderName":"沈淮","text":"谁敢打你？","timestamp":"2026-07-02T12:34:55.960Z","roundId":"group_round_1782995689947_zyo9c1s","userId":"uid_1782055845928_hyeor3ki7","characterId":"group_1782994777858","_id":5615},{"id":1782999726994,"sender":"them","senderCharId":"d6b63bf1-a46c-4feb-89c9-0c675b5e5a48","senderName":"沈淮","text":"你直接说！","timestamp":"2026-07-02T12:34:56.616Z","roundId":"group_round_1782995689947_zyo9c1s","userId":"uid_1782055845928_hyeor3ki7","characterId":"group_1782994777858","_id":5616},{"id":1782999726995,"sender":"them","senderCharId":"d6b63bf1-a46c-4feb-89c9-0c675b5e5a48","senderName":"沈淮","text":"是不是景泽哥欺负你了？还是在外面有别的小妖精了","timestamp":"2026-07-02T12:34:59.406Z","roundId":"group_round_1782995689947_zyo9c1s","userId":"uid_1782055845928_hyeor3ki7","characterId":"group_1782994777858","_id":5617},{"id":1782999726996,"sender":"them","senderCharId":"08502714-5fd1-4152-ac01-88d5d4e84008","senderName":"范景泽","text":"说吧，没关系。","timestamp":"2026-07-02T12:35:00.762Z","roundId":"group_round_1782995689947_zyo9c1s","userId":"uid_1782055845928_hyeor3ki7","characterId":"group_1782994777858","_id":5618},{"id":1782999726997,"sender":"them","senderCharId":"08502714-5fd1-4152-ac01-88d5d4e84008","senderName":"范景泽","text":"不管是什么事，我都不会生气的。","timestamp":"2026-07-02T12:35:03.197Z","roundId":"group_round_1782995689947_zyo9c1s","userId":"uid_1782055845928_hyeor3ki7","characterId":"group_1782994777858","_id":5619},{"id":1782999726998,"sender":"them","text":"宝宝你别吓我，你是不是想甩了我","timestamp":"2026-07-02T12:35:06.427Z","source":"group_dm","groupId":"group_1782994777858","groupName":"恩","rawContent":"宝宝你别吓我，你是不是想甩了我","isHtml":false,"userId":"uid_1782055845928_hyeor3ki7","characterId":"d6b63bf1-a46c-4feb-89c9-0c675b5e5a48","_id":5620},{"id":1782999726999,"sender":"me","text":"我好像同时喜欢上两个人了……","replyTo":null,"timestamp":"2026-07-02T12:35:16.767Z","userId":"uid_1782055845928_hyeor3ki7","characterId":"group_1782994777858","_id":5621},{"id":1782999727000,"sender":"them","senderCharId":"d6b63bf1-a46c-4feb-89c9-0c675b5e5a48","senderName":"沈淮","text":"？？？？？","timestamp":"2026-07-02T12:36:07.800Z","roundId":"group_round_1782995717452_jg71s81","userId":"uid_1782055845928_hyeor3ki7","characterId":"group_1782994777858","_id":5622},{"id":1782999727001,"sender":"them","senderCharId":"d6b63bf1-a46c-4feb-89c9-0c675b5e5a48","senderName":"沈淮","text":"等会儿 哪两个？？","timestamp":"2026-07-02T12:36:08.789Z","roundId":"group_round_1782995717452_jg71s81","userId":"uid_1782055845928_hyeor3ki7","characterId":"group_1782994777858","_id":5623},{"id":1782999727002,"sender":"them","senderCharId":"d6b63bf1-a46c-4feb-89c9-0c675b5e5a48","senderName":"沈淮","text":"宝宝你把话说清楚 里面有我吗 (开始吸氧","timestamp":"2026-07-02T12:36:10.362Z","roundId":"group_round_1782995717452_jg71s81","userId":"uid_1782055845928_hyeor3ki7","characterId":"group_1782994777858","_id":5624},{"id":1782999727003,"sender":"them","senderCharId":"08502714-5fd1-4152-ac01-88d5d4e84008","senderName":"范景泽","text":"...","timestamp":"2026-07-02T12:36:11.200Z","roundId":"group_round_1782995717452_jg71s81","userId":"uid_1782055845928_hyeor3ki7","characterId":"group_1782994777858","_id":5625},{"id":1782999727004,"sender":"them","senderCharId":"08502714-5fd1-4152-ac01-88d5d4e84008","senderName":"范景泽","text":"另外一个是沈淮吗","timestamp":"2026-07-02T12:36:12.854Z","roundId":"group_round_1782995717452_jg71s81","userId":"uid_1782055845928_hyeor3ki7","characterId":"group_1782994777858","_id":5626},{"id":1782999727005,"sender":"them","senderCharId":"d6b63bf1-a46c-4feb-89c9-0c675b5e5a48","senderName":"沈淮","text":"我靠 景泽哥你别这么直接 我害怕","timestamp":"2026-07-02T12:36:14.480Z","roundId":"group_round_1782995717452_jg71s81","userId":"uid_1782055845928_hyeor3ki7","characterId":"group_1782994777858","_id":5627},{"id":1782999727006,"sender":"them","text":"宝宝你疯啦！！你怎么在群里说这个！！","timestamp":"2026-07-02T12:36:17.743Z","source":"group_dm","groupId":"group_1782994777858","groupName":"恩","userId":"uid_1782055845928_hyeor3ki7","characterId":"d6b63bf1-a46c-4feb-89c9-0c675b5e5a48","_id":5628},{"id":1782999727007,"sender":"them","text":"你是不是不想要我了 呜呜呜你是不是想选景泽哥","timestamp":"2026-07-02T12:36:20.880Z","source":"group_dm","groupId":"group_1782994777858","groupName":"恩","userId":"uid_1782055845928_hyeor3ki7","characterId":"d6b63bf1-a46c-4feb-89c9-0c675b5e5a48","_id":5629},{"id":1782999727008,"sender":"them","text":"外卖快到了，先吃东西。","timestamp":"2026-07-02T12:36:23.200Z","source":"group_dm","groupId":"group_1782994777858","groupName":"恩","userId":"uid_1782055845928_hyeor3ki7","characterId":"08502714-5fd1-4152-ac01-88d5d4e84008","_id":5630},{"id":1782999727009,"sender":"them","text":"如果是真的，等我等下回去，我们见面慢慢谈。","timestamp":"2026-07-02T12:36:26.685Z","source":"group_dm","groupId":"group_1782994777858","groupName":"恩","userId":"uid_1782055845928_hyeor3ki7","characterId":"08502714-5fd1-4152-ac01-88d5d4e84008","_id":5631},{"id":1782999727010,"sender":"me","text":"嗯……","replyTo":null,"timestamp":"2026-07-02T12:36:44.323Z","userId":"uid_1782055845928_hyeor3ki7","characterId":"group_1782994777858","_id":5632},{"id":1782999727011,"sender":"me","sticker":"https://nos.netease.com/ysf/f6d6883855020e9321dd5b4e08b4c2d2.jpg","text":"表情包：宝贝对不起","timestamp":"2026-07-02T12:36:47.599Z","userId":"uid_1782055845928_hyeor3ki7","characterId":"group_1782994777858","_id":5633},{"id":1782999727012,"sender":"me","text":"可是这件事最近真的一直困扰着我","replyTo":null,"timestamp":"2026-07-02T12:36:56.695Z","userId":"uid_1782055845928_hyeor3ki7","characterId":"group_1782994777858","_id":5634},{"id":1782999727013,"sender":"me","text":"所以我最近都没怎么看消息","replyTo":null,"timestamp":"2026-07-02T12:37:03.427Z","userId":"uid_1782055845928_hyeor3ki7","characterId":"group_1782994777858","_id":5635},{"id":1782999727014,"sender":"them","senderCharId":"d6b63bf1-a46c-4feb-89c9-0c675b5e5a48","senderName":"沈淮","text":"你别跟我对不起啊 我心慌","timestamp":"2026-07-02T12:38:30.539Z","replyTo":{"id":1782999727011,"text":"表情包：宝贝对不起","sender":"me","senderName":"","sticker":"https://nos.netease.com/ysf/f6d6883855020e9321dd5b4e08b4c2d2.jpg"},"roundId":"group_round_1782995824989_b7o3mtb","userId":"uid_1782055845928_hyeor3ki7","characterId":"group_1782994777858","_id":5636},{"id":1782999727015,"sender":"them","senderCharId":"d6b63bf1-a46c-4feb-89c9-0c675b5e5a48","senderName":"沈淮","text":"所以你最近躲着我 就是在纠结这个吗","timestamp":"2026-07-02T12:38:32.121Z","roundId":"group_round_1782995824989_b7o3mtb","userId":"uid_1782055845928_hyeor3ki7","characterId":"group_1782994777858","_id":5637},{"id":1782999727016,"sender":"them","senderCharId":"08502714-5fd1-4152-ac01-88d5d4e84008","senderName":"范景泽","text":"沈淮 别吵她","timestamp":"2026-07-02T12:38:33.404Z","roundId":"group_round_1782995824989_b7o3mtb","userId":"uid_1782055845928_hyeor3ki7","characterId":"group_1782994777858","_id":5638},{"id":1782999727017,"sender":"them","senderCharId":"08502714-5fd1-4152-ac01-88d5d4e84008","senderName":"范景泽","text":"胆胆 别给自己太大压力 粥应该快到了 先吃点东西","timestamp":"2026-07-02T12:38:36.235Z","roundId":"group_round_1782995824989_b7o3mtb","userId":"uid_1782055845928_hyeor3ki7","characterId":"group_1782994777858","_id":5639},{"id":1782999727018,"sender":"them","senderCharId":"d6b63bf1-a46c-4feb-89c9-0c675b5e5a48","senderName":"沈淮","text":"我哪有吵她 我都要急死了","timestamp":"2026-07-02T12:38:37.896Z","roundId":"group_round_1782995824989_b7o3mtb","userId":"uid_1782055845928_hyeor3ki7","characterId":"group_1782994777858","_id":5640,"rawContent":"我哪有吵她 我都要急死了","isHtml":false,"edited":true},{"id":1782999727019,"sender":"them","text":"宝宝你认真的吗 景泽哥还在群里呢 你怎么直接承认了啊","timestamp":"2026-07-02T12:38:41.172Z","source":"group_dm","groupId":"group_1782994777858","groupName":"恩","userId":"uid_1782055845928_hyeor3ki7","characterId":"d6b63bf1-a46c-4feb-89c9-0c675b5e5a48","_id":5641},{"id":1782999727020,"sender":"them","text":"你是不是更喜欢他 呜呜呜我不管 晚上我也要过去 凭什么他能回家我不行","timestamp":"2026-07-02T12:38:44.597Z","source":"group_dm","groupId":"group_1782994777858","groupName":"恩","userId":"uid_1782055845928_hyeor3ki7","characterId":"d6b63bf1-a46c-4feb-89c9-0c675b5e5a48","_id":5642},{"id":1782999727021,"sender":"them","text":"别怕 我没有生气","timestamp":"2026-07-02T12:38:46.349Z","source":"group_dm","groupId":"group_1782994777858","groupName":"恩","userId":"uid_1782055845928_hyeor3ki7","characterId":"08502714-5fd1-4152-ac01-88d5d4e84008","_id":5643},{"id":1782999727022,"sender":"them","text":"路有些堵 我大概还有十五分钟到家 别胡思乱想","timestamp":"2026-07-02T12:38:49.281Z","source":"group_dm","groupId":"group_1782994777858","groupName":"恩","userId":"uid_1782055845928_hyeor3ki7","characterId":"08502714-5fd1-4152-ac01-88d5d4e84008","_id":5644},{"id":1782999727023,"sender":"me","text":"你们是什么看法……","replyTo":null,"timestamp":"2026-07-02T12:39:00.656Z","userId":"uid_1782055845928_hyeor3ki7","characterId":"group_1782994777858","_id":5645},{"id":1782999727024,"sender":"me","text":"真的很抱歉","replyTo":null,"timestamp":"2026-07-02T12:39:03.346Z","userId":"uid_1782055845928_hyeor3ki7","characterId":"group_1782994777858","_id":5646},{"id":1782999727025,"sender":"me","sticker":"https://img.heliar.top/file/1780302240227_IMG_3104.jpeg","text":"表情包：我原本是一个特别可爱的人 你们知道吗 然后冲出来一堆人一堆事 把我给毁了","timestamp":"2026-07-02T12:39:11.100Z","userId":"uid_1782055845928_hyeor3ki7","characterId":"group_1782994777858","_id":5647},{"id":1782990725869,"text":"……你们一起来呗","sender":"me","time":"20:39","timestamp":1782995977735,"replyTo":null,"userId":"uid_1782055845928_hyeor3ki7","characterId":"d6b63bf1-a46c-4feb-89c9-0c675b5e5a48","_id":5648},{"id":1782999727026,"sender":"them","senderCharId":"d6b63bf1-a46c-4feb-89c9-0c675b5e5a48","senderName":"沈淮","text":"我能有什么看法 只要你不把我甩了 怎么都行","timestamp":"2026-07-02T12:40:43.439Z","replyTo":{"id":1782999727023,"text":"你们是什么看法……","sender":"me","senderName":""},"roundId":"group_round_1782995952826_s2y28o5","userId":"uid_1782055845928_hyeor3ki7","characterId":"group_1782994777858","_id":5649,"rawContent":"我能有什么看法 只要你不把我甩了 怎么都行","isHtml":false,"edited":true}]