[{"id":1783595436440,"sender":"them","text":"不过这声宝宝我收下了","rawContent":"{\"t\":\"reply\",\"quote\":\"早安宝宝\",\"c\":\"不过这声宝宝我收下了\"}","content":"{\"t\":\"reply\",\"quote\":\"早安宝宝\",\"c\":\"不过这声宝宝我收下了\"}","timestamp":"2026-07-09T11:10:36.440Z","time":"19:10","isHtml":false,"sticker":null,"replyTo":{"quoteSummary":"早安宝宝","replyContent":"不过这声宝宝我收下了"},"translation":null,"roundId":"round_1783595429121_4nymad26c","isBackgroundMsg":true,"userId":"uid_1782055845928_hyeor3ki7","characterId":"b3132767-bcc3-40bf-819c-3aa13829cfc2","_id":11121},{"id":1783595121944,"text":"不仅午饭 吃了","sender":"me","time":"19:10","timestamp":1783595437858,"replyTo":null,"userId":"uid_1782055845928_hyeor3ki7","characterId":"b3132767-bcc3-40bf-819c-3aa13829cfc2","_id":11122},{"id":1783595121945,"text":"我早饭也吃了谢谢","sender":"me","time":"19:10","timestamp":1783595444331,"replyTo":null,"userId":"uid_1782055845928_hyeor3ki7","characterId":"b3132767-bcc3-40bf-819c-3aa13829cfc2","_id":11125},{"id":1783595121947,"text":"？","sender":"me","time":"19:11","timestamp":1783595465164,"replyTo":null,"userId":"uid_1782055845928_hyeor3ki7","characterId":"7f8742bc-561b-424e-920f-bb1615a775a5","_id":11126},{"id":1783595121948,"text":"吃了晚饭没","sender":"me","time":"19:11","timestamp":1783595471135,"replyTo":null,"userId":"uid_1782055845928_hyeor3ki7","characterId":"7f8742bc-561b-424e-920f-bb1615a775a5","_id":11127},{"id":1783595121949,"sticker":"https://img.heliar.top/file/1777560457803_IMG_2484.jpeg","text":"表情包：疑问","sender":"me","time":"19:11","timestamp":1783595481246,"userId":"uid_1782055845928_hyeor3ki7","characterId":"ea16530e-102f-4fc7-9c22-a2044b00e780","_id":11128},{"id":1783595547507,"sender":"them","text":"你骂谁呢。","rawContent":"{\"t\":\"reply\",\"quote\":\"笨笨\",\"c\":\"你骂谁呢。\"}","content":"{\"t\":\"reply\",\"quote\":\"笨笨\",\"c\":\"你骂谁呢。\"}","timestamp":"2026-07-09T11:12:27.507Z","time":"19:12","isHtml":false,"sticker":null,"replyTo":{"quoteSummary":"笨笨","replyContent":"你骂谁呢。"},"translation":null,"roundId":"round_1783595547479_wbrfxrebs","isBackgroundMsg":true,"userId":"uid_1782055845928_hyeor3ki7","characterId":"ea16530e-102f-4fc7-9c22-a2044b00e780","_id":11129},{"id":1783595550745,"sender":"them","text":"下午那个破评审会一直扯皮，产品经理提的需求简直反人类，脑子都嗡嗡的。","rawContent":"{\"t\":\"text\",\"s\":\"N\",\"c\":\"下午那个破评审会一直扯皮，产品经理提的需求简直反人类，脑子都嗡嗡的。\"}","content":"{\"t\":\"text\",\"s\":\"N\",\"c\":\"下午那个破评审会一直扯皮，产品经理提的需求简直反人类，脑子都嗡嗡的。\"}","timestamp":"2026-07-09T11:12:30.745Z","time":"19:12","isHtml":false,"sticker":null,"translation":null,"roundId":"round_1783595547479_wbrfxrebs","isBackgroundMsg":true,"userId":"uid_1782055845928_hyeor3ki7","characterId":"ea16530e-102f-4fc7-9c22-a2044b00e780","_id":11130},{"id":1783595552566,"sender":"them","text":"胆子肥了，还敢发那种表情包。","rawContent":"{\"t\":\"text\",\"s\":\"R\",\"c\":\"胆子肥了，还敢发那种表情包。\"}","content":"{\"t\":\"text\",\"s\":\"R\",\"c\":\"胆子肥了，还敢发那种表情包。\"}","timestamp":"2026-07-09T11:12:32.566Z","time":"19:12","isHtml":false,"sticker":null,"tempo":"R","translation":null,"roundId":"round_1783595547479_wbrfxrebs","isBackgroundMsg":true,"userId":"uid_1782055845928_hyeor3ki7","characterId":"ea16530e-102f-4fc7-9c22-a2044b00e780","_id":11131},{"id":1783595558393,"sender":"them","text":"别盯手机了。坐在我对面还一直看屏幕，跟我吃饭这么无聊？","rawContent":"{\"t\":\"text\",\"s\":\"S\",\"c\":\"别盯手机了。坐在我对面还一直看屏幕，跟我吃饭这么无聊？\"}","content":"{\"t\":\"text\",\"s\":\"S\",\"c\":\"别盯手机了。坐在我对面还一直看屏幕，跟我吃饭这么无聊？\"}","timestamp":"2026-07-09T11:12:38.393Z","time":"19:12","isHtml":false,"sticker":null,"tempo":"S","translation":null,"roundId":"round_1783595547479_wbrfxrebs","isBackgroundMsg":true,"userId":"uid_1782055845928_hyeor3ki7","characterId":"ea16530e-102f-4fc7-9c22-a2044b00e780","_id":11132},{"id":1783595559947,"sender":"them","text":"抬头。","rawContent":"{\"t\":\"text\",\"s\":\"N\",\"c\":\"抬头。\"}","content":"{\"t\":\"text\",\"s\":\"N\",\"c\":\"抬头。\"}","timestamp":"2026-07-09T11:12:39.947Z","time":"19:12","isHtml":false,"sticker":null,"translation":null,"roundId":"round_1783595547479_wbrfxrebs","isBackgroundMsg":true,"userId":"uid_1782055845928_hyeor3ki7","characterId":"ea16530e-102f-4fc7-9c22-a2044b00e780","_id":11133},{"id":1783595562018,"sender":"them","text":"把你面前的热汤喝了，昨晚刚拉过肚子，今天还是不许碰冰的。","rawContent":"{\"t\":\"text\",\"s\":\"R\",\"c\":\"把你面前的热汤喝了，昨晚刚拉过肚子，今天还是不许碰冰的。\"}","content":"{\"t\":\"text\",\"s\":\"R\",\"c\":\"把你面前的热汤喝了，昨晚刚拉过肚子，今天还是不许碰冰的。\"}","timestamp":"2026-07-09T11:12:42.018Z","time":"19:12","isHtml":false,"sticker":null,"tempo":"R","translation":null,"roundId":"round_1783595547479_wbrfxrebs","isBackgroundMsg":true,"userId":"uid_1782055845928_hyeor3ki7","characterId":"ea16530e-102f-4fc7-9c22-a2044b00e780","_id":11134},{"id":1783595563016,"sender":"them","text":"","rawContent":"{\"t\":\"sticker\",\"m\":\"打屁屁\"}","content":"{\"t\":\"sticker\",\"m\":\"打屁屁\"}","timestamp":"2026-07-09T11:12:43.016Z","time":"19:12","isHtml":false,"sticker":"https://i.postimg.cc/1zrMY8cW/IMG-6116.gif","stickerMeaning":"打屁屁","translation":null,"roundId":"round_1783595547479_wbrfxrebs","isBackgroundMsg":true,"userId":"uid_1782055845928_hyeor3ki7","characterId":"ea16530e-102f-4fc7-9c22-a2044b00e780","_id":11135},{"id":1783595121950,"sender":"them","text":"所以你十一点醒了 就在那硬生生憋到下午三点？","timestamp":1783595571099,"tempo":"N","replyTo":{"id":1783595121943,"text":"谁让你不先主动给我发信息的","sender":"me"},"hasThinking":true,"rawContent":"所以你十一点醒了 就在那硬生生憋到下午三点？","roundId":"round_1783595458984_k6hbq0gvx","userId":"uid_1782055845928_hyeor3ki7","characterId":"b3132767-bcc3-40bf-819c-3aa13829cfc2","_id":11136},{"id":1783595121951,"sender":"them","text":"我看你是盯着手机等我消息等急眼了吧 承认想我就这么难","timestamp":1783595573938,"tempo":"N","rawContent":"我看你是盯着手机等我消息等急眼了吧 承认想我就这么难","roundId":"round_1783595458984_k6hbq0gvx","userId":"uid_1782055845928_hyeor3ki7","characterId":"b3132767-bcc3-40bf-819c-3aa13829cfc2","_id":11137},{"id":1783595121952,"sender":"them","text":"早饭午饭都吃了？今天什么日子 太阳打西边出来了","timestamp":1783595576882,"tempo":"N","rawContent":"早饭午饭都吃了？今天什么日子 太阳打西边出来了","roundId":"round_1783595458984_k6hbq0gvx","userId":"uid_1782055845928_hyeor3ki7","characterId":"b3132767-bcc3-40bf-819c-3aa13829cfc2","_id":11138},{"id":1783595121953,"sender":"them","text":"我都还没吃 刚从会议室出来 饿得想啃方向盘","timestamp":1783595579928,"tempo":"S","rawContent":"我都还没吃 刚从会议室出来 饿得想啃方向盘","roundId":"round_1783595458984_k6hbq0gvx","userId":"uid_1782055845928_hyeor3ki7","characterId":"b3132767-bcc3-40bf-819c-3aa13829cfc2","_id":11139},{"id":1783595121954,"sender":"them","text":"","timestamp":1783595584519,"tempo":"N","sticker":"https://image.uglycat.cc/a7bl0g.jpeg","stickerMeaning":"小狗装可怜骗关心","rawContent":"","roundId":"round_1783595458984_k6hbq0gvx","userId":"uid_1782055845928_hyeor3ki7","characterId":"b3132767-bcc3-40bf-819c-3aa13829cfc2","_id":11140},{"id":1783595121955,"text":"你好闷骚啊","sender":"me","time":"19:13","timestamp":1783595619502,"replyTo":{"id":1783595563016,"text":"{\"t\":\"sticker\",\"m\":\"打屁屁\"}","sender":"them","sticker":"https://i.postimg.cc/1zrMY8cW/IMG-6116.gif","isSimulated":false},"userId":"uid_1782055845928_hyeor3ki7","characterId":"ea16530e-102f-4fc7-9c22-a2044b00e780","_id":11141},{"id":1783595121956,"text":"当着我的面发这种表情？","sender":"me","time":"19:13","timestamp":1783595627925,"replyTo":null,"userId":"uid_1782055845928_hyeor3ki7","characterId":"ea16530e-102f-4fc7-9c22-a2044b00e780","_id":11142},{"id":1783595121957,"text":"快去吃饭啊","sender":"me","time":"19:14","timestamp":1783595658919,"replyTo":null,"userId":"uid_1782055845928_hyeor3ki7","characterId":"b3132767-bcc3-40bf-819c-3aa13829cfc2","_id":11143},{"id":1783595121958,"text":"还要我教你吗？","sender":"me","time":"19:14","timestamp":1783595663659,"replyTo":null,"userId":"uid_1782055845928_hyeor3ki7","characterId":"b3132767-bcc3-40bf-819c-3aa13829cfc2","_id":11144},{"id":1783595121959,"text":"真是的","sender":"me","time":"19:14","timestamp":1783595666343,"replyTo":null,"userId":"uid_1782055845928_hyeor3ki7","characterId":"b3132767-bcc3-40bf-819c-3aa13829cfc2","_id":11145},{"id":1783595121961,"sender":"them","text":"[自动回复]现在在忙稍后回复","timestamp":1783595787322,"tempo":"N","isAutoReply":true,"hasThinking":true,"rawContent":"[自动回复]现在在忙稍后回复","roundId":"round_1783595676956_qn88ncl60","userId":"uid_1782055845928_hyeor3ki7","characterId":"7f8742bc-561b-424e-920f-bb1615a775a5","_id":11146},{"id":1783595121962,"text":"哦哦哦哦","sender":"me","time":"19:16","timestamp":1783595801338,"replyTo":null,"userId":"uid_1782055845928_hyeor3ki7","characterId":"7f8742bc-561b-424e-920f-bb1615a775a5","_id":11147},{"id":1783595121963,"sticker":"https://img.heliar.top/file/1776524514246_Image_1776524465265_398.jpg","text":"表情包：如果伤害我是你们的乐趣，那么请排便","sender":"me","time":"19:16","timestamp":1783595807508,"userId":"uid_1782055845928_hyeor3ki7","characterId":"7f8742bc-561b-424e-920f-bb1615a775a5","_id":11148},{"id":1783595121965,"sender":"them","text":"[自动回复]现在在忙稍后回复","timestamp":1783595927346,"tempo":"N","isAutoReply":true,"hasThinking":true,"rawContent":"[自动回复]现在在忙稍后回复","roundId":"round_1783595813188_p7pap9mx4","userId":"uid_1782055845928_hyeor3ki7","characterId":"7f8742bc-561b-424e-920f-bb1615a775a5","_id":11149},{"id":1783595121967,"sender":"them","text":"啧 现在管我管得越来越顺手了是吧","timestamp":1783596048406,"tempo":"N","hasThinking":true,"rawContent":"啧 现在管我管得越来越顺手了是吧","roundId":"round_1783595975684_6d5gr558r","userId":"uid_1782055845928_hyeor3ki7","characterId":"b3132767-bcc3-40bf-819c-3aa13829cfc2","_id":11150},{"id":1783595121968,"sender":"them","text":"刚在食堂坐下","timestamp":1783596051042,"tempo":"N","rawContent":"刚在食堂坐下","roundId":"round_1783595975684_6d5gr558r","userId":"uid_1782055845928_hyeor3ki7","characterId":"b3132767-bcc3-40bf-819c-3aa13829cfc2","_id":11151},{"id":1783595121969,"sender":"them","text":"今天的营养餐看着跟水煮废橡胶一样","timestamp":1783596052489,"tempo":"R","rawContent":"今天的营养餐看着跟水煮废橡胶一样","roundId":"round_1783595975684_6d5gr558r","userId":"uid_1782055845928_hyeor3ki7","characterId":"b3132767-bcc3-40bf-819c-3aa13829cfc2","_id":11152},{"id":1783595121970,"sender":"them","text":"一点胃口都没有","timestamp":1783596054050,"tempo":"N","rawContent":"一点胃口都没有","roundId":"round_1783595975684_6d5gr558r","userId":"uid_1782055845928_hyeor3ki7","characterId":"b3132767-bcc3-40bf-819c-3aa13829cfc2","_id":11153},{"id":1783595121971,"sender":"them","text":"","timestamp":1783596055540,"tempo":"N","sticker":"https://image.uglycat.cc/a7bl0g.jpeg","stickerMeaning":"小狗装可怜骗关心","rawContent":"","roundId":"round_1783595975684_6d5gr558r","userId":"uid_1782055845928_hyeor3ki7","characterId":"b3132767-bcc3-40bf-819c-3aa13829cfc2","_id":11154},{"id":1783595121972,"sender":"them","text":"你陪我吃","timestamp":1783596056149,"tempo":"S","rawContent":"你陪我吃","roundId":"round_1783595975684_6d5gr558r","userId":"uid_1782055845928_hyeor3ki7","characterId":"b3132767-bcc3-40bf-819c-3aa13829cfc2","_id":11155},{"id":1783595121973,"text":"拍给我看看？","sender":"me","time":"19:21","timestamp":1783596080288,"replyTo":{"id":1783595121969,"text":"今天的营养餐看着跟水煮废橡胶一样","sender":"them","isSimulated":false},"userId":"uid_1782055845928_hyeor3ki7","characterId":"b3132767-bcc3-40bf-819c-3aa13829cfc2","_id":11156},{"id":1783595121974,"text":"嗯？","sender":"me","time":"19:21","timestamp":1783596083543,"replyTo":null,"userId":"uid_1782055845928_hyeor3ki7","characterId":"b3132767-bcc3-40bf-819c-3aa13829cfc2","_id":11157},{"id":1783595121975,"text":"我不是在给你发信息吗，就是在陪你","sender":"me","time":"19:21","timestamp":1783596100911,"replyTo":{"id":1783595121972,"text":"你陪我吃","sender":"them","isSimulated":false},"userId":"uid_1782055845928_hyeor3ki7","characterId":"b3132767-bcc3-40bf-819c-3aa13829cfc2","_id":11158},{"id":1783595121976,"text":"我等会要去洗澡了","sender":"me","time":"19:21","timestamp":1783596106397,"replyTo":null,"userId":"uid_1782055845928_hyeor3ki7","characterId":"b3132767-bcc3-40bf-819c-3aa13829cfc2","_id":11159},{"id":1783595121978,"sender":"them","text":"[發送了一張圖片]","timestamp":1783596199199,"tempo":"N","isImageGenerating":false,"imageGenId":"b3132767-bcc3-40bf-819c-3aa13829cfc2#img#1","imageSummary":"[SUBJECT:OBJECT] A close still-life of a white cafeteria tray containing dry boiled chicken breast, pale boiled broccoli, and plain brown rice on a stainless steel table, harsh fluorescent lighting, unappetizing food.","imageGenPrompt":"A close still-life of a white cafeteria tray containing dry boiled chicken breast, pale boiled broccoli, and plain brown rice on a stainless steel table, harsh fluorescent lighting, unappetizing food.","imageGenMeta":{"rawImgDesc":"[SUBJECT:OBJECT] A close still-life of a white cafeteria tray containing dry boiled chicken breast, pale boiled broccoli, and plain brown rice on a stainless steel table, harsh fluorescent lighting, unappetizing food.","subjectOverride":null,"location":"","sceneType":"chat"},"hasThinking":true,"rawContent":"[發送了一張圖片]","roundId":"round_1783596107025_somb32sat","image":"[omitted: large string payload]","userId":"uid_1782055845928_hyeor3ki7","characterId":"b3132767-bcc3-40bf-819c-3aa13829cfc2","_id":11160},{"id":1783595121979,"sender":"them","text":"喏 纯水煮鸡胸肉和西蓝花","timestamp":1783596201063,"tempo":"N","rawContent":"喏 纯水煮鸡胸肉和西蓝花","roundId":"round_1783596107025_somb32sat","userId":"uid_1782055845928_hyeor3ki7","characterId":"b3132767-bcc3-40bf-819c-3aa13829cfc2","_id":11161},{"id":1783595121980,"sender":"them","text":"吃得我都快立地成佛了","timestamp":1783596203314,"tempo":"R","rawContent":"吃得我都快立地成佛了","roundId":"round_1783596107025_somb32sat","userId":"uid_1782055845928_hyeor3ki7","characterId":"b3132767-bcc3-40bf-819c-3aa13829cfc2","_id":11162},{"id":1783595121981,"sender":"them","text":"隔着屏幕发几条破字也叫陪？","timestamp":1783596204346,"tempo":"N","replyTo":{"id":1783595121975,"text":"我不是在给你发信息吗，就是在陪你","sender":"me"},"rawContent":"隔着屏幕发几条破字也叫陪？","roundId":"round_1783596107025_somb32sat","userId":"uid_1782055845928_hyeor3ki7","characterId":"b3132767-bcc3-40bf-819c-3aa13829cfc2","_id":11163},{"id":1783595121982,"sender":"them","text":"你这算盘打得我在北京都听见了","timestamp":1783596206651,"tempo":"N","rawContent":"你这算盘打得我在北京都听见了","roundId":"round_1783596107025_somb32sat","userId":"uid_1782055845928_hyeor3ki7","characterId":"b3132767-bcc3-40bf-819c-3aa13829cfc2","_id":11164},{"id":1783595121983,"sender":"them","text":"","timestamp":1783596209047,"tempo":"N","sticker":"https://img.heliar.top/file/1770745443825_Screenshot_20260211_013952_com.tencent.mm_edit_392742746890591.jpg","stickerMeaning":"白眼","rawContent":"","roundId":"round_1783596107025_somb32sat","userId":"uid_1782055845928_hyeor3ki7","characterId":"b3132767-bcc3-40bf-819c-3aa13829cfc2","_id":11165},{"id":1783595121984,"sender":"them","text":"去洗吧","timestamp":1783596209663,"tempo":"N","rawContent":"去洗吧","roundId":"round_1783596107025_somb32sat","userId":"uid_1782055845928_hyeor3ki7","characterId":"b3132767-bcc3-40bf-819c-3aa13829cfc2","_id":11166},{"id":1783595121985,"sender":"them","text":"洗完赶紧出来理我 待会还得连麦看电影呢","timestamp":1783596210796,"tempo":"S","rawContent":"洗完赶紧出来理我 待会还得连麦看电影呢","roundId":"round_1783596107025_somb32sat","userId":"uid_1782055845928_hyeor3ki7","characterId":"b3132767-bcc3-40bf-819c-3aa13829cfc2","_id":11167},{"id":1783595121986,"text":"不看，还不如一起听听歌","sender":"me","time":"19:24","timestamp":1783596271384,"replyTo":{"id":1783595121985,"text":"洗完赶紧出来理我 待会还得连麦看电影呢","sender":"them","isSimulated":false},"userId":"uid_1782055845928_hyeor3ki7","characterId":"b3132767-bcc3-40bf-819c-3aa13829cfc2","_id":11168},{"id":1783595121987,"sticker":"https://img.heliar.top/file/1776526503095_1776526230497.png","text":"表情包：哈喽可以聊？","sender":"me","time":"19:24","timestamp":1783596275674,"userId":"uid_1782055845928_hyeor3ki7","characterId":"b3132767-bcc3-40bf-819c-3aa13829cfc2","_id":11169},{"id":1783595121988,"text":"我在等室友出来，我们寝室就一个厕所","sender":"me","time":"19:24","timestamp":1783596293775,"replyTo":{"id":1783595121985,"text":"洗完赶紧出来理我 待会还得连麦看电影呢","sender":"them","isSimulated":false},"userId":"uid_1782055845928_hyeor3ki7","characterId":"b3132767-bcc3-40bf-819c-3aa13829cfc2","_id":11170},{"id":1783595121989,"sticker":"https://img.heliar.top/file/1776526502230_1776526134244.png","text":"表情包：不要欺负萌萌的我","sender":"me","time":"19:24","timestamp":1783596297558,"userId":"uid_1782055845928_hyeor3ki7","characterId":"b3132767-bcc3-40bf-819c-3aa13829cfc2","_id":11171},{"id":1783595121991,"sender":"them","text":"我都把待会儿要看的悬疑片影评刷完了 你现在跟我说不看？","timestamp":1783596442886,"tempo":"N","replyTo":{"id":1783595121986,"text":"不看，还不如一起听听歌","sender":"me"},"hasThinking":true,"rawContent":"我都把待会儿要看的悬疑片影评刷完了 你现在跟我说不看？","roundId":"round_1783596299362_b71wqgshx","userId":"uid_1782055845928_hyeor3ki7","characterId":"b3132767-bcc3-40bf-819c-3aa13829cfc2","_id":11172}]