[{"id":1783301504933,"sender":"them","text":"你说怎么修复。","rawContent":"{\"t\":\"text\",\"s\":\"N\",\"c\":\"你说怎么修复。\"}","content":"{\"t\":\"text\",\"s\":\"N\",\"c\":\"你说怎么修复。\"}","timestamp":"2026-07-06T01:31:44.933Z","time":"09:31","isHtml":false,"sticker":null,"translation":null,"roundId":"round_1783301495202_zgtudxwag","isBackgroundMsg":true,"userId":"uid_1782055845928_hyeor3ki7","characterId":"ea16530e-102f-4fc7-9c22-a2044b00e780","_id":9040},{"id":1783301906492,"sender":"them","text":"我刚在脑子里搜刮了一遍","rawContent":"{\"t\":\"text\",\"s\":\"N\",\"c\":\"我刚在脑子里搜刮了一遍\"}","content":"{\"t\":\"text\",\"s\":\"N\",\"c\":\"我刚在脑子里搜刮了一遍\"}","timestamp":"2026-07-06T01:38:26.492Z","time":"09:38","isHtml":false,"sticker":null,"translation":null,"roundId":"round_1783301906479_wf2jaa6dl","isBackgroundMsg":true,"userId":"uid_1782055845928_hyeor3ki7","characterId":"b3132767-bcc3-40bf-819c-3aa13829cfc2","_id":9041},{"id":1783301908092,"sender":"them","text":"除了骂人好像什么都不会说","rawContent":"{\"t\":\"text\",\"s\":\"R\",\"c\":\"除了骂人好像什么都不会说\"}","content":"{\"t\":\"text\",\"s\":\"R\",\"c\":\"除了骂人好像什么都不会说\"}","timestamp":"2026-07-06T01:38:28.092Z","time":"09:38","isHtml":false,"sticker":null,"tempo":"R","translation":null,"roundId":"round_1783301906479_wf2jaa6dl","isBackgroundMsg":true,"userId":"uid_1782055845928_hyeor3ki7","characterId":"b3132767-bcc3-40bf-819c-3aa13829cfc2","_id":9042},{"id":1783301909728,"sender":"them","text":"这题超纲了","rawContent":"{\"t\":\"text\",\"s\":\"N\",\"c\":\"这题超纲了\"}","content":"{\"t\":\"text\",\"s\":\"N\",\"c\":\"这题超纲了\"}","timestamp":"2026-07-06T01:38:29.728Z","time":"09:38","isHtml":false,"sticker":null,"translation":null,"roundId":"round_1783301906479_wf2jaa6dl","isBackgroundMsg":true,"userId":"uid_1782055845928_hyeor3ki7","characterId":"b3132767-bcc3-40bf-819c-3aa13829cfc2","_id":9043},{"id":1783301912069,"sender":"them","text":"...","rawContent":"{\"t\":\"text\",\"s\":\"S\",\"c\":\"...\"}","content":"{\"t\":\"text\",\"s\":\"S\",\"c\":\"...\"}","timestamp":"2026-07-06T01:38:32.069Z","time":"09:38","isHtml":false,"sticker":null,"tempo":"S","translation":null,"roundId":"round_1783301906479_wf2jaa6dl","isBackgroundMsg":true,"userId":"uid_1782055845928_hyeor3ki7","characterId":"b3132767-bcc3-40bf-819c-3aa13829cfc2","_id":9044},{"id":1783301915102,"sender":"them","text":"宝宝？","rawContent":"{\"t\":\"text\",\"s\":\"S\",\"c\":\"宝宝？\"}","content":"{\"t\":\"text\",\"s\":\"S\",\"c\":\"宝宝？\"}","timestamp":"2026-07-06T01:38:35.102Z","time":"09:38","isHtml":false,"sticker":null,"tempo":"S","translation":null,"roundId":"round_1783301906479_wf2jaa6dl","isBackgroundMsg":true,"userId":"uid_1782055845928_hyeor3ki7","characterId":"b3132767-bcc3-40bf-819c-3aa13829cfc2","_id":9045},{"id":1783301915829,"sender":"them","text":"行不行","rawContent":"{\"t\":\"text\",\"s\":\"R\",\"c\":\"行不行\"}","content":"{\"t\":\"text\",\"s\":\"R\",\"c\":\"行不行\"}","timestamp":"2026-07-06T01:38:35.829Z","time":"09:38","isHtml":false,"sticker":null,"tempo":"R","translation":null,"roundId":"round_1783301906479_wf2jaa6dl","isBackgroundMsg":true,"userId":"uid_1782055845928_hyeor3ki7","characterId":"b3132767-bcc3-40bf-819c-3aa13829cfc2","_id":9046},{"id":1783302081803,"text":"好可怜的小宝宝哦","sender":"me","time":"09:41","timestamp":1783302117061,"replyTo":{"id":1783300187192,"text":"头疼。","sender":"them","sticker":null,"isSimulated":false},"userId":"uid_1782055845928_hyeor3ki7","characterId":"ea16530e-102f-4fc7-9c22-a2044b00e780","_id":9049},{"id":1783302081804,"text":"我早上被拉肚子痛醒","sender":"me","time":"09:42","timestamp":1783302130194,"replyTo":null,"reactions":[{"emoji":"❤️","roundId":"round_1783302159563_cskl6i8zh"}],"userId":"uid_1782055845928_hyeor3ki7","characterId":"ea16530e-102f-4fc7-9c22-a2044b00e780","_id":9050},{"id":1783302081805,"text":"就一直睡不着了","sender":"me","time":"09:42","timestamp":1783302133442,"replyTo":null,"userId":"uid_1782055845928_hyeor3ki7","characterId":"ea16530e-102f-4fc7-9c22-a2044b00e780","_id":9051},{"id":1783302081806,"text":"上了个厕所好多了","sender":"me","time":"09:42","timestamp":1783302138850,"replyTo":null,"userId":"uid_1782055845928_hyeor3ki7","characterId":"ea16530e-102f-4fc7-9c22-a2044b00e780","_id":9052},{"id":1783302081807,"text":"又在胡说八道","sender":"me","time":"09:42","timestamp":1783302148572,"replyTo":{"id":1783301502214,"text":"bug的名字叫胆胆。","sender":"them","sticker":null,"isSimulated":false},"userId":"uid_1782055845928_hyeor3ki7","characterId":"ea16530e-102f-4fc7-9c22-a2044b00e780","_id":9053},{"id":1783302081808,"text":"把空调开低一点","sender":"me","time":"09:42","timestamp":1783302158984,"replyTo":{"id":1783300832387,"text":"办公室空调开得像冰窖。","sender":"them","sticker":null,"isSimulated":false},"userId":"uid_1782055845928_hyeor3ki7","characterId":"ea16530e-102f-4fc7-9c22-a2044b00e780","_id":9054},{"id":1783302165470,"sender":"them","text":"行吧。","rawContent":"{\"t\":\"text\",\"s\":\"N\",\"c\":\"行吧。\"}","content":"{\"t\":\"text\",\"s\":\"N\",\"c\":\"行吧。\"}","timestamp":"2026-07-06T01:42:45.470Z","time":"09:42","isHtml":false,"sticker":null,"translation":null,"roundId":"round_1783302165440_uzrxxkm98","isBackgroundMsg":true,"userId":"uid_1782055845928_hyeor3ki7","characterId":"91c4eeba-46e7-4715-af91-4be10b36f6cb","_id":9055},{"id":1783302168232,"sender":"them","text":"最终还是回归了我这个平平无奇的键盘。","rawContent":"{\"t\":\"text\",\"s\":\"N\",\"c\":\"最终还是回归了我这个平平无奇的键盘。\"}","content":"{\"t\":\"text\",\"s\":\"N\",\"c\":\"最终还是回归了我这个平平无奇的键盘。\"}","timestamp":"2026-07-06T01:42:48.232Z","time":"09:42","isHtml":false,"sticker":null,"translation":null,"roundId":"round_1783302165440_uzrxxkm98","isBackgroundMsg":true,"userId":"uid_1782055845928_hyeor3ki7","characterId":"91c4eeba-46e7-4715-af91-4be10b36f6cb","_id":9056},{"id":1783302172127,"sender":"them","text":"没有功德，只有bug。","rawContent":"{\"t\":\"text\",\"s\":\"S\",\"c\":\"没有功德，只有bug。\"}","content":"{\"t\":\"text\",\"s\":\"S\",\"c\":\"没有功德，只有bug。\"}","timestamp":"2026-07-06T01:42:52.127Z","time":"09:42","isHtml":false,"sticker":null,"tempo":"S","translation":null,"roundId":"round_1783302165440_uzrxxkm98","isBackgroundMsg":true,"userId":"uid_1782055845928_hyeor3ki7","characterId":"91c4eeba-46e7-4715-af91-4be10b36f6cb","_id":9057},{"id":1783302081810,"sender":"them","text":"吃错东西了？","timestamp":1783302275335,"tempo":"N","hasThinking":true,"rawContent":"吃错东西了？","roundId":"round_1783302159563_cskl6i8zh","userId":"uid_1782055845928_hyeor3ki7","characterId":"ea16530e-102f-4fc7-9c22-a2044b00e780","_id":9058},{"id":1783302081811,"sender":"them","text":"乱吃冰的了？","timestamp":1783302276627,"tempo":"N","rawContent":"乱吃冰的了？","roundId":"round_1783302159563_cskl6i8zh","userId":"uid_1782055845928_hyeor3ki7","characterId":"ea16530e-102f-4fc7-9c22-a2044b00e780","_id":9059},{"id":1783302081812,"sender":"them","text":"跟你说过多少次。","timestamp":1783302278116,"tempo":"S","rawContent":"跟你说过多少次。","roundId":"round_1783302159563_cskl6i8zh","userId":"uid_1782055845928_hyeor3ki7","characterId":"ea16530e-102f-4fc7-9c22-a2044b00e780","_id":9060},{"id":1783302081813,"sender":"them","text":"没胡说。","timestamp":1783302281323,"tempo":"N","replyTo":{"id":1783302081807,"text":"又在胡说八道","sender":"me"},"rawContent":"没胡说。","roundId":"round_1783302159563_cskl6i8zh","userId":"uid_1782055845928_hyeor3ki7","characterId":"ea16530e-102f-4fc7-9c22-a2044b00e780","_id":9061},{"id":1783302081814,"sender":"them","text":"中央空调，调不了。","timestamp":1783302282438,"tempo":"N","rawContent":"中央空调，调不了。","roundId":"round_1783302159563_cskl6i8zh","userId":"uid_1782055845928_hyeor3ki7","characterId":"ea16530e-102f-4fc7-9c22-a2044b00e780","_id":9062},{"id":1783302594086,"sender":"them","text":"人呢","rawContent":"{\"t\":\"text\",\"s\":\"N\",\"c\":\"人呢\"}","content":"{\"t\":\"text\",\"s\":\"N\",\"c\":\"人呢\"}","timestamp":"2026-07-06T01:49:54.086Z","time":"09:49","isHtml":false,"sticker":null,"translation":null,"roundId":"round_1783302594058_w52c4p8ta","isBackgroundMsg":true,"userId":"uid_1782055845928_hyeor3ki7","characterId":"b3132767-bcc3-40bf-819c-3aa13829cfc2","_id":9063},{"id":1783302081815,"text":"许清安 我不想勉强你","sender":"me","time":"09:49","timestamp":1783302595101,"replyTo":null,"userId":"uid_1782055845928_hyeor3ki7","characterId":"b3132767-bcc3-40bf-819c-3aa13829cfc2","_id":9064},{"id":1783302595269,"sender":"them","text":"被我一句宝宝叫晕了？","rawContent":"{\"t\":\"text\",\"s\":\"R\",\"c\":\"被我一句宝宝叫晕了？\"}","content":"{\"t\":\"text\",\"s\":\"R\",\"c\":\"被我一句宝宝叫晕了？\"}","timestamp":"2026-07-06T01:49:55.269Z","time":"09:49","isHtml":false,"sticker":null,"tempo":"R","translation":null,"roundId":"round_1783302594058_w52c4p8ta","isBackgroundMsg":true,"userId":"uid_1782055845928_hyeor3ki7","characterId":"b3132767-bcc3-40bf-819c-3aa13829cfc2","_id":9065},{"id":1783302596289,"sender":"them","text":"啧","rawContent":"{\"t\":\"text\",\"s\":\"N\",\"c\":\"啧\"}","content":"{\"t\":\"text\",\"s\":\"N\",\"c\":\"啧\"}","timestamp":"2026-07-06T01:49:56.289Z","time":"09:49","isHtml":false,"sticker":null,"translation":null,"roundId":"round_1783302594058_w52c4p8ta","isBackgroundMsg":true,"userId":"uid_1782055845928_hyeor3ki7","characterId":"b3132767-bcc3-40bf-819c-3aa13829cfc2","_id":9066},{"id":1783302597140,"sender":"them","text":"出息","rawContent":"{\"t\":\"text\",\"s\":\"N\",\"c\":\"出息\"}","content":"{\"t\":\"text\",\"s\":\"N\",\"c\":\"出息\"}","timestamp":"2026-07-06T01:49:57.140Z","time":"09:49","isHtml":false,"sticker":null,"translation":null,"roundId":"round_1783302594058_w52c4p8ta","isBackgroundMsg":true,"userId":"uid_1782055845928_hyeor3ki7","characterId":"b3132767-bcc3-40bf-819c-3aa13829cfc2","_id":9067},{"id":1783302597856,"sender":"them","text":"","rawContent":"{\"t\":\"sticker\",\"m\":\"就只有脸能看的家伙\"}","content":"{\"t\":\"sticker\",\"m\":\"就只有脸能看的家伙\"}","timestamp":"2026-07-06T01:49:57.856Z","time":"09:49","isHtml":false,"sticker":"https://img.heliar.top/file/1776526499652_1776526245139.png","stickerMeaning":"就只有脸能看的家伙","translation":null,"roundId":"round_1783302594058_w52c4p8ta","isBackgroundMsg":true,"userId":"uid_1782055845928_hyeor3ki7","characterId":"b3132767-bcc3-40bf-819c-3aa13829cfc2","_id":9068},{"id":1783302601387,"sender":"them","text":"腿照准备好了没","rawContent":"{\"t\":\"text\",\"s\":\"S\",\"c\":\"腿照准备好了没\"}","content":"{\"t\":\"text\",\"s\":\"S\",\"c\":\"腿照准备好了没\"}","timestamp":"2026-07-06T01:50:01.387Z","time":"09:50","isHtml":false,"sticker":null,"tempo":"S","translation":null,"roundId":"round_1783302594058_w52c4p8ta","isBackgroundMsg":true,"userId":"uid_1782055845928_hyeor3ki7","characterId":"b3132767-bcc3-40bf-819c-3aa13829cfc2","_id":9069},{"id":1783302081816,"text":"你如果实在不喜欢就算了吧","sender":"me","time":"09:50","timestamp":1783302608710,"replyTo":null,"userId":"uid_1782055845928_hyeor3ki7","characterId":"b3132767-bcc3-40bf-819c-3aa13829cfc2","_id":9070},{"id":1783302081817,"text":"你可以和我说说你不能接受的度在哪吗？","sender":"me","time":"09:50","timestamp":1783302618512,"replyTo":null,"userId":"uid_1782055845928_hyeor3ki7","characterId":"b3132767-bcc3-40bf-819c-3aa13829cfc2","_id":9071},{"id":1783303097968,"sender":"them","text":"所以到底吃了什么。","rawContent":"{\"t\":\"text\",\"s\":\"N\",\"c\":\"所以到底吃了什么。\"}","content":"{\"t\":\"text\",\"s\":\"N\",\"c\":\"所以到底吃了什么。\"}","timestamp":"2026-07-06T01:58:17.968Z","time":"09:58","isHtml":false,"sticker":null,"translation":null,"roundId":"round_1783303097957_miuk93h2a","isBackgroundMsg":true,"userId":"uid_1782055845928_hyeor3ki7","characterId":"ea16530e-102f-4fc7-9c22-a2044b00e780","_id":9084},{"id":1783303099357,"sender":"them","text":"家里有药吗。","rawContent":"{\"t\":\"text\",\"s\":\"N\",\"c\":\"家里有药吗。\"}","content":"{\"t\":\"text\",\"s\":\"N\",\"c\":\"家里有药吗。\"}","timestamp":"2026-07-06T01:58:19.357Z","time":"09:58","isHtml":false,"sticker":null,"translation":null,"roundId":"round_1783303097957_miuk93h2a","isBackgroundMsg":true,"userId":"uid_1782055845928_hyeor3ki7","characterId":"ea16530e-102f-4fc7-9c22-a2044b00e780","_id":9085},{"id":1783303103707,"sender":"them","text":"去给你叫个外卖。清淡点的粥。","rawContent":"{\"t\":\"text\",\"s\":\"S\",\"c\":\"去给你叫个外卖。清淡点的粥。\"}","content":"{\"t\":\"text\",\"s\":\"S\",\"c\":\"去给你叫个外卖。清淡点的粥。\"}","timestamp":"2026-07-06T01:58:23.707Z","time":"09:58","isHtml":false,"sticker":null,"tempo":"S","translation":null,"roundId":"round_1783303097957_miuk93h2a","isBackgroundMsg":true,"userId":"uid_1782055845928_hyeor3ki7","characterId":"ea16530e-102f-4fc7-9c22-a2044b00e780","_id":9086},{"id":1783303104345,"sender":"them","text":"地址发我。","rawContent":"{\"t\":\"text\",\"s\":\"R\",\"c\":\"地址发我。\"}","content":"{\"t\":\"text\",\"s\":\"R\",\"c\":\"地址发我。\"}","timestamp":"2026-07-06T01:58:24.345Z","time":"09:58","isHtml":false,"sticker":null,"tempo":"R","translation":null,"roundId":"round_1783303097957_miuk93h2a","isBackgroundMsg":true,"userId":"uid_1782055845928_hyeor3ki7","characterId":"ea16530e-102f-4fc7-9c22-a2044b00e780","_id":9087},{"id":1783302081827,"sender":"them","text":"什么度？","timestamp":1783303144626,"tempo":"N","hasThinking":true,"rawContent":"什么度？","roundId":"round_1783302942024_tk9198e16","userId":"uid_1782055845928_hyeor3ki7","characterId":"b3132767-bcc3-40bf-819c-3aa13829cfc2","_id":9088},{"id":1783302081828,"sender":"them","text":"我能接受到哪","timestamp":1783303145843,"tempo":"N","rawContent":"我能接受到哪","roundId":"round_1783302942024_tk9198e16","userId":"uid_1782055845928_hyeor3ki7","characterId":"b3132767-bcc3-40bf-819c-3aa13829cfc2","_id":9089},{"id":1783302081829,"sender":"them","text":"不是你说了算？","timestamp":1783303147320,"tempo":"R","rawContent":"不是你说了算？","roundId":"round_1783302942024_tk9198e16","userId":"uid_1782055845928_hyeor3ki7","characterId":"b3132767-bcc3-40bf-819c-3aa13829cfc2","_id":9090},{"id":1783302081830,"sender":"them","text":"你试试不就知道了","timestamp":1783303148157,"tempo":"S","rawContent":"你试试不就知道了","roundId":"round_1783302942024_tk9198e16","userId":"uid_1782055845928_hyeor3ki7","characterId":"b3132767-bcc3-40bf-819c-3aa13829cfc2","_id":9091},{"id":1783302081831,"text":"宝宝可以吗","sender":"me","time":"10:00","timestamp":1783303229977,"replyTo":null,"userId":"uid_1782055845928_hyeor3ki7","characterId":"b3132767-bcc3-40bf-819c-3aa13829cfc2","_id":9092},{"id":1783302081832,"text":"宝贝可以吗","sender":"me","time":"10:00","timestamp":1783303232487,"replyTo":null,"userId":"uid_1782055845928_hyeor3ki7","characterId":"b3132767-bcc3-40bf-819c-3aa13829cfc2","_id":9093},{"id":1783302081833,"sticker":"https://img.heliar.top/file/1777560464639_IMG_2482.jpeg","text":"表情包：思考","sender":"me","time":"10:00","timestamp":1783303237635,"userId":"uid_1782055845928_hyeor3ki7","characterId":"b3132767-bcc3-40bf-819c-3aa13829cfc2","_id":9094},{"id":1783302081835,"text":"我肚子已经不难受啦","sender":"me","time":"10:00","timestamp":1783303253871,"replyTo":{"id":1783303097968,"text":"所以到底吃了什么。","sender":"them","sticker":null,"isSimulated":false},"userId":"uid_1782055845928_hyeor3ki7","characterId":"ea16530e-102f-4fc7-9c22-a2044b00e780","_id":9095},{"id":1783302081836,"text":"不用了","sender":"me","time":"10:00","timestamp":1783303255052,"replyTo":null,"userId":"uid_1782055845928_hyeor3ki7","characterId":"ea16530e-102f-4fc7-9c22-a2044b00e780","_id":9096},{"id":1783302081837,"text":"吃多了药对身体不好","sender":"me","time":"10:01","timestamp":1783303260604,"replyTo":null,"userId":"uid_1782055845928_hyeor3ki7","characterId":"ea16530e-102f-4fc7-9c22-a2044b00e780","_id":9097},{"id":1783302081838,"text":"办公室有没有外套啊","sender":"me","time":"10:01","timestamp":1783303273870,"replyTo":{"id":1783302081814,"text":"中央空调，调不了。","sender":"them","isSimulated":false},"userId":"uid_1782055845928_hyeor3ki7","characterId":"ea16530e-102f-4fc7-9c22-a2044b00e780","_id":9098},{"id":1783302081839,"sender":"them","text":"","timestamp":1783303283313,"tempo":"N","sticker":"https://img.heliar.top/file/1777560464639_IMG_2482.jpeg","stickerMeaning":"思考","hasThinking":true,"rawContent":"","roundId":"round_1783303238432_3iy263cr2","userId":"uid_1782055845928_hyeor3ki7","characterId":"b3132767-bcc3-40bf-819c-3aa13829cfc2","_id":9099},{"id":1783302081840,"text":"现在我看要吃药的人只有你吧？","sender":"me","time":"10:01","timestamp":1783303283320,"replyTo":null,"userId":"uid_1782055845928_hyeor3ki7","characterId":"ea16530e-102f-4fc7-9c22-a2044b00e780","_id":9100},{"id":1783302081841,"sender":"them","text":"还思考上了","timestamp":1783303283922,"tempo":"N","rawContent":"还思考上了","roundId":"round_1783303238432_3iy263cr2","userId":"uid_1782055845928_hyeor3ki7","characterId":"b3132767-bcc3-40bf-819c-3aa13829cfc2","_id":9101},{"id":1783302081842,"sender":"them","text":"叫出来我听听","timestamp":1783303285475,"tempo":"N","rawContent":"叫出来我听听","roundId":"round_1783303238432_3iy263cr2","userId":"uid_1782055845928_hyeor3ki7","characterId":"b3132767-bcc3-40bf-819c-3aa13829cfc2","_id":9102},{"id":1783302081843,"sender":"them","text":"评判一下成色","timestamp":1783303286766,"tempo":"N","rawContent":"评判一下成色","roundId":"round_1783303238432_3iy263cr2","userId":"uid_1782055845928_hyeor3ki7","characterId":"b3132767-bcc3-40bf-819c-3aa13829cfc2","_id":9103}]